cgtroll/__init__.py
cgtroll/__main__.py
cgtroll-1.0.1.dist-info/LICENSE
cgtroll-1.0.1.dist-info/METADATA
cgtroll-1.0.1.dist-info/WHEEL
cgtroll-1.0.1.dist-info/top_level.txt
cgtroll-1.0.1.dist-info/RECORD
