Metadata-Version: 2.1
Name: cgtroll
Version: 1.0.1
Summary: Convert your python code to any language supported by codingame to troll the language ranking.
Author-email: FrequentlyMissedDeadlines <FrequentlyMissedDeadlines+cgtroll@gmail.com>
Project-URL: Homepage, https://github.com/FrequentlyMissedDeadlines/cgtroll
Project-URL: Bug Reports, https://github.com/FrequentlyMissedDeadlines/cgtroll/issues
Project-URL: Source, https://github.com/FrequentlyMissedDeadlines/cgtroll
Keywords: CodinGame
Classifier: Programming Language :: Python :: 3
Classifier: License :: OSI Approved :: MIT License
Classifier: Operating System :: OS Independent
Classifier: Development Status :: 5 - Production/Stable
Classifier: Intended Audience :: End Users/Desktop
Classifier: Natural Language :: English
Classifier: Topic :: Software Development
Classifier: Programming Language :: Python :: 3.7
Classifier: Programming Language :: Python :: 3.8
Classifier: Programming Language :: Python :: 3.9
Classifier: Programming Language :: Python :: 3.10
Classifier: Programming Language :: Python :: 3.11
Requires-Python: >=3.7
License-File: LICENSE
